hyperlink/__init__.py
hyperlink/_socket.py
hyperlink/_url.py
hyperlink/hypothesis.py
hyperlink/py.typed
hyperlink/test/__init__.py
hyperlink/test/common.py
hyperlink/test/test_common.py
hyperlink/test/test_decoded_url.py
hyperlink/test/test_hypothesis.py
hyperlink/test/test_parse.py
hyperlink/test/test_scheme_registration.py
hyperlink/test/test_socket.py
hyperlink/test/test_url.py
hyperlink-20.0.0.dist-info/DESCRIPTION.rst
hyperlink-20.0.0.dist-info/METADATA
hyperlink-20.0.0.dist-info/RECORD
hyperlink-20.0.0.dist-info/WHEEL
hyperlink-20.0.0.dist-info/metadata.json
hyperlink-20.0.0.dist-info/top_level.txt
